melaxtool/Textclass.py
melaxtool/__init__.py
melaxtool/melaxapi.py
melaxtool-0.0.3.dist-info/LICENSE
melaxtool-0.0.3.dist-info/METADATA
melaxtool-0.0.3.dist-info/WHEEL
melaxtool-0.0.3.dist-info/top_level.txt
melaxtool-0.0.3.dist-info/RECORD
