Metadata-Version: 2.1
Name: melaxtool
Version: 0.0.3
Summary: this is simple tool for melaxtech nlp
Home-page: UNKNOWN
Author: melax
Author-email: UNKNOWN
License: UNKNOWN
Platform: UNKNOWN
Requires-Dist: requests
